{
  "updAt": "2026-01-24",
  "id": 9192,
  "sym": "USHL",
  "rpt": [
    {
      "id": 5905,
      "qtr": {
        "id": 1,
        "qtrNm": "First Quarter"
      },
      "rptTyp": {
        "id": 2,
        "rptNm": "Quarterly Report"
      },
      "fy": {
        "id": 41,
        "fyNm": "2025-2026",
        "fromYr": "2025-07-17",
        "toYr": "2026-07-16",
        "fyNmNp": "2082-2083"
      },
      "pe": 83.02,
      "eps": 1.67,
      "paidUp": 220000000,
      "profit": 916179,
      "nwps": 92.25
    },
    {
      "id": 5793,
      "rptTyp": {
        "id": 1,
        "rptNm": "Annual Report"
      },
      "fy": {
        "id": 40,
        "fyNm": "2024-2025",
        "fromYr": "2024-07-16",
        "toYr": "2025-07-16",
        "fyNmNp": "2081-2082"
      },
      "pe": 18.82,
      "eps": 32.88,
      "paidUp": 220000000,
      "profit": 72342556,
      "nwps": 91.83
    },
    {
      "id": 5788,
      "rptTyp": {
        "id": 1,
        "rptNm": "Annual Report"
      },
      "fy": {
        "id": 34,
        "fyNm": "2021-2022",
        "fromYr": "2021-07-16",
        "toYr": "2022-07-16",
        "fyNmNp": "2078-2079"
      },
      "pe": -6.83,
      "eps": -14.63,
      "paidUp": 133000000,
      "profit": 19456437,
      "nwps": 84.54
    },
    {
      "id": 5637,
      "qtr": {
        "id": 4,
        "qtrNm": "Fourth Quarter"
      },
      "rptTyp": {
        "id": 2,
        "rptNm": "Quarterly Report"
      },
      "fy": {
        "id": 40,
        "fyNm": "2024-2025",
        "fromYr": "2024-07-16",
        "toYr": "2025-07-16",
        "fyNmNp": "2081-2082"
      },
      "pe": 81.34,
      "eps": 34.66,
      "paidUp": 220000000,
      "profit": 92555595,
      "nwps": 93.61
    },
    {
      "id": 5253,
      "qtr": {
        "id": 3,
        "qtrNm": "Third Quarter"
      },
      "rptTyp": {
        "id": 2,
        "rptNm": "Quarterly Report"
      },
      "fy": {
        "id": 40,
        "fyNm": "2024-2025",
        "fromYr": "2024-07-16",
        "toYr": "2025-07-16",
        "fyNmNp": "2081-2082"
      },
      "pe": 53.65,
      "eps": -2.06,
      "paidUp": 220000000,
      "profit": -1132342,
      "nwps": 51.54
    },
    {
      "id": 4972,
      "qtr": {
        "id": 2,
        "qtrNm": "Second Quarter"
      },
      "rptTyp": {
        "id": 2,
        "rptNm": "Quarterly Report"
      },
      "fy": {
        "id": 40,
        "fyNm": "2024-2025",
        "fromYr": "2024-07-16",
        "toYr": "2025-07-16",
        "fyNmNp": "2081-2082"
      },
      "pe": 44.06,
      "eps": -3.4,
      "paidUp": 220000000,
      "profit": -1869215,
      "nwps": 52.06
    },
    {
      "id": 4813,
      "qtr": {
        "id": 1,
        "qtrNm": "First Quarter"
      },
      "rptTyp": {
        "id": 2,
        "rptNm": "Quarterly Report"
      },
      "fy": {
        "id": 40,
        "fyNm": "2024-2025",
        "fromYr": "2024-07-16",
        "toYr": "2025-07-16",
        "fyNmNp": "2081-2082"
      },
      "pe": 39.22,
      "eps": -24.18,
      "paidUp": 220000000,
      "profit": -13296515,
      "nwps": 52.91
    },
    {
      "id": 4579,
      "qtr": {
        "id": 1,
        "qtrNm": "First Quarter"
      },
      "rptTyp": {
        "id": 2,
        "rptNm": "Quarterly Report"
      },
      "fy": {
        "id": 40,
        "fyNm": "2024-2025",
        "fromYr": "2024-07-16",
        "toYr": "2025-07-16",
        "fyNmNp": "2081-2082"
      },
      "pe": 39.22,
      "eps": -24.18,
      "paidUp": 220000000,
      "profit": -13296515,
      "nwps": 239.09
    },
    {
      "id": 4445,
      "rptTyp": {
        "id": 1,
        "rptNm": "Annual Report"
      },
      "fy": {
        "id": 39,
        "fyNm": "2023-2024",
        "fromYr": "2023-07-17",
        "toYr": "2024-07-15",
        "fyNmNp": "2080-2081"
      },
      "pe": 64,
      "eps": -7,
      "paidUp": 220000000,
      "profit": 16135373,
      "nwps": 59
    },
    {
      "id": 4444,
      "rptTyp": {
        "id": 1,
        "rptNm": "Annual Report"
      },
      "fy": {
        "id": 39,
        "fyNm": "2023-2024",
        "fromYr": "2023-07-17",
        "toYr": "2024-07-15",
        "fyNmNp": "2080-2081"
      },
      "pe": 64,
      "eps": -7,
      "paidUp": 220000000,
      "profit": 16135373,
      "nwps": 59
    },
    {
      "id": 4244,
      "qtr": {
        "id": 4,
        "qtrNm": "Fourth Quarter"
      },
      "rptTyp": {
        "id": 2,
        "rptNm": "Quarterly Report"
      },
      "fy": {
        "id": 39,
        "fyNm": "2023-2024",
        "fromYr": "2023-07-17",
        "toYr": "2024-07-15",
        "fyNmNp": "2080-2081"
      },
      "pe": 63.11,
      "eps": -7.88,
      "paidUp": 220000000,
      "profit": -13941373,
      "nwps": 58.41
    },
    {
      "id": 4242,
      "qtr": {
        "id": 4,
        "qtrNm": "Fourth Quarter"
      },
      "rptTyp": {
        "id": 2,
        "rptNm": "Quarterly Report"
      },
      "fy": {
        "id": 39,
        "fyNm": "2023-2024",
        "fromYr": "2023-07-17",
        "toYr": "2024-07-15",
        "fyNmNp": "2080-2081"
      },
      "pe": 63.11,
      "eps": -7.88,
      "paidUp": 220000000,
      "profit": -13941373,
      "nwps": 58.41
    },
    {
      "id": 3983,
      "qtr": {
        "id": 3,
        "qtrNm": "Third Quarter"
      },
      "rptTyp": {
        "id": 2,
        "rptNm": "Quarterly Report"
      },
      "fy": {
        "id": 39,
        "fyNm": "2023-2024",
        "fromYr": "2023-07-17",
        "toYr": "2024-07-15",
        "fyNmNp": "2080-2081"
      },
      "pe": 104.68,
      "eps": 4.91,
      "paidUp": 220000000,
      "profit": 8104876,
      "nwps": 64.73
    },
    {
      "id": 3868,
      "qtr": {
        "id": 2,
        "qtrNm": "Second Quarter"
      },
      "rptTyp": {
        "id": 2,
        "rptNm": "Quarterly Report"
      },
      "fy": {
        "id": 39,
        "fyNm": "2023-2024",
        "fromYr": "2023-07-17",
        "toYr": "2024-07-15",
        "fyNmNp": "2080-2081"
      },
      "pe": 0.64,
      "eps": 0.44,
      "paidUp": 220000000,
      "profit": 970703,
      "nwps": 61.4
    },
    {
      "id": 3866,
      "qtr": {
        "id": 2,
        "qtrNm": "Second Quarter"
      },
      "rptTyp": {
        "id": 2,
        "rptNm": "Quarterly Report"
      },
      "fy": {
        "id": 39,
        "fyNm": "2023-2024",
        "fromYr": "2023-07-17",
        "toYr": "2024-07-15",
        "fyNmNp": "2080-2081"
      },
      "pe": 0.64,
      "eps": 0.44,
      "paidUp": 220000000,
      "profit": 970703,
      "nwps": 61.4
    },
    {
      "id": 3617,
      "rptTyp": {
        "id": 1,
        "rptNm": "Annual Report"
      },
      "fy": {
        "id": 38,
        "fyNm": "2022-2023",
        "fromYr": "2022-07-17",
        "toYr": "2023-07-16",
        "fyNmNp": "2079-2080"
      },
      "pe": 0,
      "eps": -23,
      "paidUp": 220000000,
      "profit": 0,
      "nwps": 67.33
    },
    {
      "id": 3590,
      "rptTyp": {
        "id": 1,
        "rptNm": "Annual Report"
      },
      "fy": {
        "id": 38,
        "fyNm": "2022-2023",
        "fromYr": "2022-07-17",
        "toYr": "2023-07-16",
        "fyNmNp": "2079-2080"
      },
      "pe": 0,
      "eps": -23,
      "paidUp": 220000000,
      "profit": 0,
      "nwps": 67.33
    },
    {
      "id": 3360,
      "qtr": {
        "id": 1,
        "qtrNm": "First Quarter"
      },
      "rptTyp": {
        "id": 2,
        "rptNm": "Quarterly Report"
      },
      "fy": {
        "id": 39,
        "fyNm": "2023-2024",
        "fromYr": "2023-07-17",
        "toYr": "2024-07-15",
        "fyNmNp": "2080-2081"
      },
      "pe": -50,
      "eps": -6.36,
      "paidUp": 220000000,
      "profit": -14001218,
      "nwps": 59.35
    },
    {
      "id": 3282,
      "qtr": {
        "id": 4,
        "qtrNm": "Fourth Quarter"
      },
      "rptTyp": {
        "id": 2,
        "rptNm": "Quarterly Report"
      },
      "fy": {
        "id": 38,
        "fyNm": "2022-2023",
        "fromYr": "2022-07-17",
        "toYr": "2023-07-16",
        "fyNmNp": "2079-2080"
      },
      "pe": 0,
      "eps": -24.94,
      "paidUp": 220000000,
      "profit": 54873793,
      "nwps": 65.71
    }
  ]
}
